MANIFEST.in
README.md
VERSION
requirements.txt
setup.cfg
setup.py
rhasspy_wake_precise_hermes.egg-info/PKG-INFO
rhasspy_wake_precise_hermes.egg-info/SOURCES.txt
rhasspy_wake_precise_hermes.egg-info/dependency_links.txt
rhasspy_wake_precise_hermes.egg-info/entry_points.txt
rhasspy_wake_precise_hermes.egg-info/requires.txt
rhasspy_wake_precise_hermes.egg-info/top_level.txt
rhasspywake_precise_hermes/__init__.py
rhasspywake_precise_hermes/__main__.py
rhasspywake_precise_hermes/precise.py
rhasspywake_precise_hermes/py.typed
rhasspywake_precise_hermes/models/athena.pb
rhasspywake_precise_hermes/models/athena.pb.params
rhasspywake_precise_hermes/models/athena.pbtxt
rhasspywake_precise_hermes/models/christopher-precise.pb
rhasspywake_precise_hermes/models/christopher-precise.pb.params
rhasspywake_precise_hermes/models/computer-en.pb
rhasspywake_precise_hermes/models/hey-mycroft-2.pb
rhasspywake_precise_hermes/models/hey-mycroft-2.pb.params
rhasspywake_precise_hermes/models/marvin.pb
rhasspywake_precise_hermes/models/marvin.pb.params
rhasspywake_precise_hermes/models/sheila-en.params
rhasspywake_precise_hermes/models/sheila-en.pb